{
  "msft_1970393556853066": {
    "id": "msft_1970393556853066",
    "company": "Microsoft",
    "title": "Product Manager",
    "location": "China, Jiangsu, Suzhou",
    "url": "https://apply.careers.microsoft.com/careers/job/1970393556853066",
    "posted_ts": 1774945261,
    "found_date": "2026-03-31T22:26:04.037636",
    "status": "new"
  },
  "msft_1970393556827633": {
    "id": "msft_1970393556827633",
    "company": "Microsoft",
    "title": "Senior Technical Product Manager",
    "location": "United States, Washington, Redmond",
    "url": "https://apply.careers.microsoft.com/careers/job/1970393556827633",
    "posted_ts": 1774301387,
    "found_date": "2026-03-31T22:26:04.037651",
    "status": "new"
  },
  "msft_1970393556752714": {
    "id": "msft_1970393556752714",
    "company": "Microsoft",
    "title": "Principal Product Manager",
    "location": "United States, Washington, Redmond",
    "url": "https://apply.careers.microsoft.com/careers/job/1970393556752714",
    "posted_ts": 1774374801,
    "found_date": "2026-03-31T22:26:04.037653",
    "status": "new"
  },
  "msft_1970393556629440": {
    "id": "msft_1970393556629440",
    "company": "Microsoft",
    "title": "Principal Product Manager",
    "location": "United States, Multiple Locations, Multiple Locations",
    "url": "https://apply.careers.microsoft.com/careers/job/1970393556629440",
    "posted_ts": 1774387217,
    "found_date": "2026-03-31T22:26:04.037655",
    "status": "new"
  },
  "msft_1970393556751424": {
    "id": "msft_1970393556751424",
    "company": "Microsoft",
    "title": "Senior Product Manager",
    "location": "United States, Washington, Redmond",
    "url": "https://apply.careers.microsoft.com/careers/job/1970393556751424",
    "posted_ts": 1774907331,
    "found_date": "2026-03-31T22:26:04.037657",
    "status": "new"
  },
  "msft_1970393556748166": {
    "id": "msft_1970393556748166",
    "company": "Microsoft",
    "title": "Principal Product Manager",
    "location": "United States, Washington, Redmond",
    "url": "https://apply.careers.microsoft.com/careers/job/1970393556748166",
    "posted_ts": 1770675297,
    "found_date": "2026-03-31T22:26:04.037658",
    "status": "new"
  },
  "msft_1970393556855371": {
    "id": "msft_1970393556855371",
    "company": "Microsoft",
    "title": "Senior Product Manager",
    "location": "India, Telangana, Hyderabad",
    "url": "https://apply.careers.microsoft.com/careers/job/1970393556855371",
    "posted_ts": 1774932243,
    "found_date": "2026-03-31T22:26:04.037660",
    "status": "new"
  },
  "msft_1970393556826718": {
    "id": "msft_1970393556826718",
    "company": "Microsoft",
    "title": "Product Manager II - Foundry Model Inference (CoreAI)",
    "location": "United States, Washington, Redmond",
    "url": "https://apply.careers.microsoft.com/careers/job/1970393556826718",
    "posted_ts": 1773099815,
    "found_date": "2026-03-31T22:26:04.037665",
    "status": "new"
  },
  "msft_1970393556768598": {
    "id": "msft_1970393556768598",
    "company": "Microsoft",
    "title": "Product Manager",
    "location": "Australia, Multiple Locations, Multiple Locations",
    "url": "https://apply.careers.microsoft.com/careers/job/1970393556768598",
    "posted_ts": 1774886400,
    "found_date": "2026-03-31T22:26:04.037667",
    "status": "new"
  },
  "msft_1970393556620243": {
    "id": "msft_1970393556620243",
    "company": "Microsoft",
    "title": "Principal Product Manager",
    "location": "United States, Multiple Locations, Multiple Locations",
    "url": "https://apply.careers.microsoft.com/careers/job/1970393556620243",
    "posted_ts": 1766004361,
    "found_date": "2026-03-31T22:26:04.037669",
    "status": "new"
  },
  "msft_1970393556853462": {
    "id": "msft_1970393556853462",
    "company": "Microsoft",
    "title": "Data Center Technician",
    "location": "Singapore, Singapore, Singapore",
    "url": "https://apply.careers.microsoft.com/careers/job/1970393556853462",
    "posted_ts": 1774948551,
    "found_date": "2026-03-31T22:26:04.659940",
    "status": "new"
  },
  "msft_1970393556853199": {
    "id": "msft_1970393556853199",
    "company": "Microsoft",
    "title": "Technical Support Engineer (Data & AI - SQL Server)",
    "location": "Japan, Tokyo-to, Tokyo",
    "url": "https://apply.careers.microsoft.com/careers/job/1970393556853199",
    "posted_ts": 1774944210,
    "found_date": "2026-03-31T22:26:04.659952",
    "status": "new"
  },
  "msft_1970393556769368": {
    "id": "msft_1970393556769368",
    "company": "Microsoft",
    "title": "Data Center Technician Manager",
    "location": "United States, Virginia, Dulles",
    "url": "https://apply.careers.microsoft.com/careers/job/1970393556769368",
    "posted_ts": 1774379973,
    "found_date": "2026-03-31T22:26:04.659954",
    "status": "new"
  },
  "msft_1970393556851288": {
    "id": "msft_1970393556851288",
    "company": "Microsoft",
    "title": "Principal Data Science Manager",
    "location": "United States, Washington, Redmond",
    "url": "https://apply.careers.microsoft.com/careers/job/1970393556851288",
    "posted_ts": 1774380351,
    "found_date": "2026-03-31T22:26:04.659955",
    "status": "new"
  },
  "msft_1970393556748774": {
    "id": "msft_1970393556748774",
    "company": "Microsoft",
    "title": "Senior Data Engineer",
    "location": "United States, Washington, Redmond",
    "url": "https://apply.careers.microsoft.com/careers/job/1970393556748774",
    "posted_ts": 1774375487,
    "found_date": "2026-03-31T22:26:04.659957",
    "status": "new"
  },
  "msft_1970393556825865": {
    "id": "msft_1970393556825865",
    "company": "Microsoft",
    "title": "Data Center Project Manager (Circular Center)",
    "location": "United States, Virginia, Boydton",
    "url": "https://apply.careers.microsoft.com/careers/job/1970393556825865",
    "posted_ts": 1774373853,
    "found_date": "2026-03-31T22:26:04.659958",
    "status": "new"
  },
  "msft_1970393556847554": {
    "id": "msft_1970393556847554",
    "company": "Microsoft",
    "title": "Data Center Program Manager",
    "location": "United States, Georgia, Atlanta",
    "url": "https://apply.careers.microsoft.com/careers/job/1970393556847554",
    "posted_ts": 1774374628,
    "found_date": "2026-03-31T22:26:04.659960",
    "status": "new"
  },
  "msft_1970393556852372": {
    "id": "msft_1970393556852372",
    "company": "Microsoft",
    "title": "Data & Applied Scientist II",
    "location": "United States, Washington, Redmond",
    "url": "https://apply.careers.microsoft.com/careers/job/1970393556852372",
    "posted_ts": 1774478126,
    "found_date": "2026-03-31T22:26:04.659962",
    "status": "new"
  },
  "msft_1970393556851038": {
    "id": "msft_1970393556851038",
    "company": "Microsoft",
    "title": "Data Center Technician Manager",
    "location": "Malaysia, Selangor, Cyberjaya",
    "url": "https://apply.careers.microsoft.com/careers/job/1970393556851038",
    "posted_ts": 1774427537,
    "found_date": "2026-03-31T22:26:04.659963",
    "status": "new"
  },
  "msft_1970393556769374": {
    "id": "msft_1970393556769374",
    "company": "Microsoft",
    "title": "Data Center IT Infra Project Manager",
    "location": "India, Telangana, Hyderabad",
    "url": "https://apply.careers.microsoft.com/careers/job/1970393556769374",
    "posted_ts": 1773144936,
    "found_date": "2026-03-31T22:26:04.659965",
    "status": "new"
  },
  "msft_1970393556814831": {
    "id": "msft_1970393556814831",
    "company": "Microsoft",
    "title": "Technical Program Manager- Advertising Measurement",
    "location": "United States, Washington, Redmond, United States, California, Mountain View",
    "url": "https://apply.careers.microsoft.com/careers/job/1970393556814831",
    "posted_ts": 1774380088,
    "found_date": "2026-03-31T22:26:05.331714",
    "status": "new"
  },
  "msft_1970393556745557": {
    "id": "msft_1970393556745557",
    "company": "Microsoft",
    "title": "Senior Data Scientist - Microsoft Advertising",
    "location": "United States, Washington, Redmond, United States, California, Mountain View",
    "url": "https://apply.careers.microsoft.com/careers/job/1970393556745557",
    "posted_ts": 1772151260,
    "found_date": "2026-03-31T22:26:05.331725",
    "status": "new"
  },
  "msft_1970393556754724": {
    "id": "msft_1970393556754724",
    "company": "Microsoft",
    "title": "Sr Account Executive(Advertising)",
    "location": "China, Beijing, Beijing",
    "url": "https://apply.careers.microsoft.com/careers/job/1970393556754724",
    "posted_ts": 1772097308,
    "found_date": "2026-03-31T22:26:05.331728",
    "status": "new"
  },
  "msft_1970393556643404": {
    "id": "msft_1970393556643404",
    "company": "Microsoft",
    "title": "Advertising Account Manager",
    "location": "United States, Texas, Austin, United States, Washington, Redmond, United States, Illinois, Chicago, United States, New York, New York, United States, Massachusetts, Boston, United States, California, San Francisco, United States, California, Mountain View",
    "url": "https://apply.careers.microsoft.com/careers/job/1970393556643404",
    "posted_ts": 1774974179,
    "found_date": "2026-03-31T22:26:05.331730",
    "status": "new"
  },
  "msft_1970393556851758": {
    "id": "msft_1970393556851758",
    "company": "Microsoft",
    "title": "Brand Advertising Designer - Motion II",
    "location": "United States, Washington, Redmond, United States, California, Mountain View",
    "url": "https://apply.careers.microsoft.com/careers/job/1970393556851758",
    "posted_ts": 1774630565,
    "found_date": "2026-03-31T22:26:05.331732",
    "status": "new"
  },
  "msft_1970393556851762": {
    "id": "msft_1970393556851762",
    "company": "Microsoft",
    "title": "Brand Advertising Designer - Digital II",
    "location": "United States, Washington, Redmond, United States, California, Mountain View",
    "url": "https://apply.careers.microsoft.com/careers/job/1970393556851762",
    "posted_ts": 1774630596,
    "found_date": "2026-03-31T22:26:05.331733",
    "status": "new"
  },
  "msft_1970393556853721": {
    "id": "msft_1970393556853721",
    "company": "Microsoft",
    "title": "Account Manager - MS Advertising",
    "location": "United States, Washington, Redmond, United States, Illinois, Chicago, United States, California, Los Angeles, United States, California, Mountain View, United States, California, San Francisco, United States, Texas, Austin",
    "url": "https://apply.careers.microsoft.com/careers/job/1970393556853721",
    "posted_ts": 1774897989,
    "found_date": "2026-03-31T22:26:05.331735",
    "status": "new"
  },
  "msft_1970393556734882": {
    "id": "msft_1970393556734882",
    "company": "Microsoft",
    "title": "Principal Software Engineer",
    "location": "United States, Washington, Redmond, United States, California, Mountain View",
    "url": "https://apply.careers.microsoft.com/careers/job/1970393556734882",
    "posted_ts": 1768941165,
    "found_date": "2026-03-31T22:26:05.331737",
    "status": "new"
  },
  "msft_1970393556749544": {
    "id": "msft_1970393556749544",
    "company": "Microsoft",
    "title": "Senior Account Manager",
    "location": "United States, New York, New York, United States, Washington, Seattle, United States, Massachusetts, Boston, United States, Illinois, Chicago, United States, California, Los Angeles, United States, Georgia, Atlanta, United States, California, San Francisco, United States, Texas, Austin",
    "url": "https://apply.careers.microsoft.com/careers/job/1970393556749544",
    "posted_ts": 1770217236,
    "found_date": "2026-03-31T22:26:05.331739",
    "status": "new"
  },
  "msft_1970393556746635": {
    "id": "msft_1970393556746635",
    "company": "Microsoft",
    "title": "Account Manager",
    "location": "United States, New York, New York, United States, Illinois, Chicago",
    "url": "https://apply.careers.microsoft.com/careers/job/1970393556746635",
    "posted_ts": 1769708579,
    "found_date": "2026-03-31T22:26:05.331741",
    "status": "new"
  },
  "msft_1970393556753614": {
    "id": "msft_1970393556753614",
    "company": "Microsoft",
    "title": "Software Engineer II - Azure Data Analytics",
    "location": "Canada, British Columbia, Vancouver",
    "url": "https://apply.careers.microsoft.com/careers/job/1970393556753614",
    "posted_ts": 1772058188,
    "found_date": "2026-03-31T22:26:05.967000",
    "status": "new"
  },
  "msft_1970393556752257": {
    "id": "msft_1970393556752257",
    "company": "Microsoft",
    "title": "Member of Technical Staff, Infrastructure Data & Analytics - MAI SuperIntelligence Team",
    "location": "United States, Multiple Locations, Multiple Locations",
    "url": "https://apply.careers.microsoft.com/careers/job/1970393556752257",
    "posted_ts": 1770672860,
    "found_date": "2026-03-31T22:26:05.967010",
    "status": "new"
  },
  "msft_1970393556753691": {
    "id": "msft_1970393556753691",
    "company": "Microsoft",
    "title": "Principal Software Engineering Manager - Data Analytics",
    "location": "Canada, British Columbia, Vancouver",
    "url": "https://apply.careers.microsoft.com/careers/job/1970393556753691",
    "posted_ts": 1771364284,
    "found_date": "2026-03-31T22:26:05.967013",
    "status": "new"
  },
  "msft_1970393556852510": {
    "id": "msft_1970393556852510",
    "company": "Microsoft",
    "title": "Sr. Data Analytics Manager",
    "location": "United States, Multiple Locations, Multiple Locations, United States, Washington, Redmond, United States, Georgia, Atlanta",
    "url": "https://apply.careers.microsoft.com/careers/job/1970393556852510",
    "posted_ts": 1774561935,
    "found_date": "2026-03-31T22:26:05.967015",
    "status": "new"
  },
  "msft_1970393556753134": {
    "id": "msft_1970393556753134",
    "company": "Microsoft",
    "title": "Sr. Technical Program Manager - Opportunity Analytics",
    "location": "United States, New York, New York",
    "url": "https://apply.careers.microsoft.com/careers/job/1970393556753134",
    "posted_ts": 1773890771,
    "found_date": "2026-03-31T22:26:05.967016",
    "status": "new"
  },
  "msft_1970393556851578": {
    "id": "msft_1970393556851578",
    "company": "Microsoft",
    "title": "HR Data Analyst, People Analytics",
    "location": "United States, Multiple Locations, Multiple Locations",
    "url": "https://apply.careers.microsoft.com/careers/job/1970393556851578",
    "posted_ts": 1774647598,
    "found_date": "2026-03-31T22:26:05.967018",
    "status": "new"
  },
  "msft_1970393556753859": {
    "id": "msft_1970393556753859",
    "company": "Microsoft",
    "title": "Senior Software Engineer | Azure Data Analytics",
    "location": "Canada, British Columbia, Vancouver",
    "url": "https://apply.careers.microsoft.com/careers/job/1970393556753859",
    "posted_ts": 1771625418,
    "found_date": "2026-03-31T22:26:05.967019",
    "status": "new"
  },
  "msft_1970393556823722": {
    "id": "msft_1970393556823722",
    "company": "Microsoft",
    "title": "Principal, Data Science & Analytics",
    "location": "United States, Washington, Redmond, United States, California, Mountain View",
    "url": "https://apply.careers.microsoft.com/careers/job/1970393556823722",
    "posted_ts": 1773790821,
    "found_date": "2026-03-31T22:26:05.967021",
    "status": "new"
  },
  "msft_1970393556826666": {
    "id": "msft_1970393556826666",
    "company": "Microsoft",
    "title": "Principal, Data Science & Analytics",
    "location": "United States, Washington, Redmond, United States, California, Mountain View",
    "url": "https://apply.careers.microsoft.com/careers/job/1970393556826666",
    "posted_ts": 1772823952,
    "found_date": "2026-03-31T22:26:05.967022",
    "status": "new"
  },
  "msft_1970393556650824": {
    "id": "msft_1970393556650824",
    "company": "Microsoft",
    "title": "Principal Data Engineer - CoreAI",
    "location": "United States, Washington, Redmond, United States, California, Mountain View",
    "url": "https://apply.careers.microsoft.com/careers/job/1970393556650824",
    "posted_ts": 1766094753,
    "found_date": "2026-03-31T22:26:05.967024",
    "status": "new"
  }
}